cqlsh/__init__.py
cqlsh/__main__.py
cqlsh/cqlsh.py
cqlshlib/__init__.py
cqlshlib/authproviderhandling.py
cqlshlib/copyutil.py
cqlshlib/cql3handling.py
cqlshlib/cqlhandling.py
cqlshlib/cqlshhandling.py
cqlshlib/displaying.py
cqlshlib/formatting.py
cqlshlib/helptopics.py
cqlshlib/pylexotron.py
cqlshlib/saferscanner.py
cqlshlib/serverversion.py
cqlshlib/sslhandling.py
cqlshlib/tracing.py
cqlshlib/util.py
cqlshlib/wcwidth.py
cqlsh-6.1.3.dist-info/LICENSE
cqlsh-6.1.3.dist-info/METADATA
cqlsh-6.1.3.dist-info/WHEEL
cqlsh-6.1.3.dist-info/entry_points.txt
cqlsh-6.1.3.dist-info/top_level.txt
cqlsh-6.1.3.dist-info/RECORD
