Metadata-Version: 2.1
Name: cqlsh
Version: 6.1.3
Summary: cqlsh is a Python-based command-line client for running CQL commands on a cassandra cluster.
Home-page: https://github.com/jeffwidman/cqlsh
Author: Jeff Widman
Author-email: jeff@jeffwidman.com
Project-URL: Changelog, https://github.com/jeffwidman/cqlsh#changelog
Project-URL: Documentation, https://cassandra.apache.org/doc/latest/tools/cqlsh.html
Keywords: cql,cassandra,cqlsh
Classifier: Development Status :: 5 - Production/Stable
Classifier: Intended Audience :: Developers
Classifier: License :: OSI Approved :: Apache Software License
Classifier: Operating System :: OS Independent
Classifier: Programming Language :: Python
Classifier: Programming Language :: Python :: 3
Classifier: Programming Language :: Python :: 3.6
Classifier: Programming Language :: Python :: 3.7
Classifier: Programming Language :: Python :: 3.8
Classifier: Programming Language :: Python :: 3.9
Classifier: Programming Language :: Python :: 3.10
Classifier: Programming Language :: Python :: 3.11
Requires-Python: >=3.6
License-File: LICENSE
Requires-Dist: cassandra-driver
Requires-Dist: six
